setup.cfg
setup.py
Soracom.egg-info/PKG-INFO
Soracom.egg-info/SOURCES.txt
Soracom.egg-info/dependency_links.txt
Soracom.egg-info/entry_points.txt
Soracom.egg-info/not-zip-safe
Soracom.egg-info/top_level.txt
soracom/__init__.py
soracom/client.py