Metadata-Version: 1.0
Name: Soracom
Version: 0.0.1.post0
Summary: SORACOM SDK for Python
Home-page: https://github.com/j3tm0t0/soracom-python
Author: MATSUI, Motokatsu
Author-email: j3tm0t0@gmail.com
License: MIT
Keywords: soracom
Platform: UNKNOWN
